falcon_client/__init__.py
falcon_client/utils.py
falcon_client/api_client/__init__.py
falcon_client/hosts/__init__.py
falcon_client/oauth2/__init__.py
falcon_client/policies/__init__.py
falcon_client-0.0.7.dist-info/.gitignore
falcon_client-0.0.7.dist-info/LICENSE
falcon_client-0.0.7.dist-info/METADATA
falcon_client-0.0.7.dist-info/WHEEL
falcon_client-0.0.7.dist-info/top_level.txt
falcon_client-0.0.7.dist-info/RECORD
