Metadata-Version: 2.1
Name: falcon-client
Version: 0.0.7
Summary: A python client to interact with CrowdStrike Falcon API.
Home-page: https://github.com/vavarachen/CSFalcon-Client.git
Author: vavarachen
Author-email: vavarachen@gmail.com
License: MIT License
Platform: UNKNOWN
Classifier: Development Status :: 3 - Alpha
Classifier: Intended Audience :: Developers
Classifier: License :: OSI Approved :: MIT License
Classifier: Natural Language :: English
Classifier: Operating System :: Microsoft
Classifier: Operating System :: POSIX :: Linux
Classifier: Operating System :: MacOS :: MacOS X
Classifier: Programming Language :: Python
Classifier: Programming Language :: Python :: 3.6
Classifier: Topic :: Software Development :: Libraries :: Python Modules
Classifier: Topic :: Software Development :: User Interfaces
Requires-Dist: requests (<3.0.0,>=2.6.0)
Requires-Dist: requests
